bytegg/__init__.py
bytegg/core.py
bytegg-0.1.4.dist-info/LICENSE
bytegg-0.1.4.dist-info/METADATA
bytegg-0.1.4.dist-info/WHEEL
bytegg-0.1.4.dist-info/top_level.txt
bytegg-0.1.4.dist-info/RECORD
