Metadata-Version: 2.1
Name: bytegg
Version: 0.1.4
Summary: A Python package that bypasses advertisements to streamline user experiences with content.
Home-page: https://github.com/KirbyHacks/ByteGG
Author: ! rL⌀w
Author-email: bytebvrd@gmail.com
License: MIT
Classifier: Development Status :: 1 - Planning
Classifier: Intended Audience :: Science/Research
Classifier: License :: OSI Approved :: MIT License
Classifier: Operating System :: POSIX :: Linux
Classifier: Programming Language :: Python :: 3
Classifier: Programming Language :: Python :: 3.4
Classifier: Programming Language :: Python :: 3.5
License-File: LICENSE
Requires-Dist: aiohttp
Requires-Dist: urllib3
